{"sud_guid": "", "sud_typ": "", "sud_nazov": "Okresný súd Žilina", "guid": "", "sud_kraj": "", "sud_okres": "", "oblast_pravnej_upravy": [], "podoblast_pravnej_upravy": [], "forma_rozhodnutia": "", "povaha_rozhodnutia": ["Zmeňujúce"], "nadpis_rozhodnutia": "", "spisova_znacka": "35T/34/2012", "identifikacne_cislo_spisu": "", "sudca_guid": "", "sudca_meno": "", "sudca_meno_text": "", "odkazovane_predpisy": [], "dokument_nazov": "", "dokument_fulltext": ["súd", "okresný", "súd", "Žilina", "spisový", "značka", "35T/34/2012", "identifikačný", "číslo", "súdny", "spis", "5112010292", "dátum", "vydať", "rozhodnúť", "23", "03", "2012", "meno", "a", "priezvisko", "sudca", "VSÚ", "JUDr", "Marek", "šenkár", "ECLI", "ECLI", "SK", "OSZA", "2012", "5112010292", "1", "oblasť", "právny", "úprava", "trestný", "právo", "-", "majetok", "povaha", "rozhodnúť", "prvostupňový", "napadnúť", "opravný", "prostriedok", "rozsudok", "v", "mena", "slovenský", "republika", "okresný", "súd", "Žilina", "v", "senát", "zložený", "z", "predseda", "senát", "JUDr", "Marek", "šenkár", "a", "člen", "senát", "Inga", "Valéria", "Hazdovej", "a", "Augustína", "Brezániho", "v", "trestný", "vec", "obvinený", "s", "i", "stíhať", "pre", "prečin", "neoprávnený", "vyrobiť", "a", "používať", "platobný", "prostriedok", "elektronický", "peniaz", "alebo", "iný", "platobný", "karty", "podľa", "§", "219", "ods", "1", "Tr", "zákon", "a", "iný", "na", "verejný", "zasadnutie", "konať", "deň", "23", "03", "2012", "o", "návrh", "na", "schválenie", "dohod", "o", "vina", "a", "trest", "takto", "r", "o", "z", "h", "o", "d", "o", "l", "podľa", "§", "334", "ods", "1", "ods", "4", "Tr", "por", "schvaľovať", "dohod", "o", "vina", "a", "trest", "z", "01", "03", "2012", "uzavretý", "medza", "prokurátor", "okresný", "prokuratúra", "Žilina", "a", "obvinený", "s", "i", "v", "nasledovný", "znenie", "obvinený", "s", "i", "nar", "XX", "XX", "XXXX", "trvale", "byt", "q", "o", "č", "XXXX/XX", "ž", "t", "č", "ÚVTOS", "g", "e", "z", "j", "e", "v", "i", "n", "n", "ý", "ž", "e", "deň", "30", "12", "2010", "v", "presne", "nezistenom", "čas", "počas", "toho", "ako", "vykonávať", "rekonštrukcia", "balkóna", "v", "byt", "vzopäť", "p", "v", "ž", "na", "Ul", "i", "č", "XXXX/XX", "sa", "nezisteným", "spôsob", "zmocnil", "plastový", "púzdra", "na", "doklad", "v", "ktorom", "sa", "nachádzať", "občiansky", "preukaz", "kartička", "poistenec", "cestovný", "pas", "kreditný", "karta", "ČSOB", "a", "M-Bank", "viesť", "na", "meno", "vzopäť", "p", "kde", "následne", "v", "čas", "od", "14", "18", "hod", "do", "15", "24", "hod", "deň", "30", "12", "2010", "prostredníctvo", "internetu", "z", "IP", "adresa", "XX", "XXX", "XXX", "XX", "vykonať", "kreditný", "karta", "č", "XXXX", "XXXX", "XXXX", "XXXX", "viesť", "k", "účtu", "v", "ČSOB", "č", "XXXXXXXXX/XXXX", "neoprávnený", "transakcia", "a", "to", "dobiť", "kredit", "na", "telefónny", "číslo", "+XXXXXXXXXXXX", "viesť", "na", "meno", "s", "i", "-", "deväť", "úspešný", "transakcia", "v", "celkový", "výška", "250", "-Eur", "a", "päť", "neúspešný", "transakcia", "v", "celkový", "výška", "96", "-Eur", "a", "neoprávnený", "transakcia", "vykonať", "u", "obchodník", "s", "názvom", "azet", "sk", "a", "s", "v", "celkový", "výška", "15", "93", "-Eur", "čím", "spôsobiť", "vzopäť", "p", "nar", "XX", "XX", "XXXX", "trvale", "byt", "ž", "Ul", "i", "č", "XXXX/XX", "celkový", "škoda", "vo", "výška", "265", "93", "-Eur", "hoci", "byť", "za", "obdobný", "čin", "v", "predchádzajúci", "dvanásť", "mesiac", "postihnúť", "mestský", "polícia", "ž", "blokový", "pokuť", "číslo", "blok", "AXXXXXXX", "zo", "deň", "12", "03", "2010", "vykonateľný", "deň", "29", "03", "2010", "zaplatiť", "na", "miesto", "vo", "výška", "30", "-Eur", "prič", "uviesť", "konať", "sa", "dopustiť", "napriek", "tomu", "že", "byť", "rozsudok", "vydať", "okresný", "súd", "Žilina", "zo", "deň", "03", "08", "2010", "právoplatný", "deň", "03", "08", "2010", "sp", "zn", "34T/127/2010", "odsúdiť", "za", "spáchať", "prečin", "krádež", "podľa", "§", "212", "ods", "2", "písm", "f", "Tr", "zákon", "a", "prečin", "poškodzovať", "cudzí", "právo", "podľa", "§", "374", "ods", "1", "písm", "a", "Tr", "zákon", "t", "e", "d", "a", "-", "si", "neoprávnene", "obstarať", "platobný", "karta", "a", "následne", "ju", "neoprávnene", "použiť", "-", "prisvojiť", "si", "cudzí", "vec", "tým", "že", "sa", "jej", "zmocnil", "prič", "byť", "za", "obdobný", "čin", "v", "predchádzajúci", "dvanásť", "mesiac", "postihnúť", "a", "byť", "za", "taký", "čin", "v", "predchádzajúci", "dvadsať", "štyri", "mesiac", "odsúdiť", "č", "í", "vzdmúť", "s", "p", "á", "vzopäť", "h", "a", "l", "-", "prečin", "neoprávnený", "vyrobiť", "a", "používať", "platobný", "prostriedok", "elektronický", "peniaz", "alebo", "iný", "platobný", "karty", "podľa", "§", "219", "ods", "1", "Tr", "zákon", "-", "prečin", "krádež", "podľa", "§", "212", "ods", "2", "písm", "f", "ods", "3", "písm", "b", "Tr", "zákon", "z", "a", "t", "o", "h", "o", "o", "d", "s", "u", "d", "z", "u", "j", "e", "podľa", "§", "44", "Tr", "zákon", "súd", "upúšťať", "od", "uložiť", "súhrnný", "trest", "podľa", "§", "42", "pretože", "pokladať", "súhrnný", "trest", "odňatia", "sloboda", "vo", "výmera", "5", "päť", "roky", "a", "10", "desať", "mesiac", "so", "zaradiť", "do", "ústav", "na", "výkon", "trest", "s", "minimálny", "stupeň", "stráženie", "ktorý", "byť", "uložiť", "rozsudok", "okresný", "súd", "Žilina", "sp", "zn", "1T/136/2011", "zo", "deň", "30", "11", "2011", "právoplatný", "a", "vykonateľný", "deň", "30", "11", "2011", "na", "ochranu", "spoločnosť", "a", "náprava", "páchateľ", "za", "dostatočný", "podľa", "§", "288", "ods", "1", "Tr", "por", "súd", "poškodený", "vzopäť", "p", "nar", "XX", "XX", "XXXX", "v", "A", "trvale", "byt", "ž", "Ul", "i", "č", "XXXX/XX", "odkazovať", "s", "jeho", "nárokom", "na", "náhrada", "škoda", "na", "občiansky", "súdny", "konať", "o", "d", "ô", "v", "o", "d", "n", "e", "n", "i", "e", "prokurátor", "okresný", "prokuratúra", "Žilina", "podať", "deň", "01", "03", "2012", "na", "okresný", "súd", "Žilina", "návrh", "na", "schválenie", "dohod", "o", "vina", "a", "trest", "v", "rozsah", "v", "ak", "byť", "uzatvoriť", "29", "02", "2012", "medza", "prokurátor", "a", "obvinený", "s", "i", "obsah", "tejto", "dohod", "jesť", "uznanie", "vina", "obvinený", "v", "celý", "rozsah", "zo", "spáchať", "stíhať", "skutok", "právny", "kvalifikovaný", "ako", "prečin", "neoprávnený", "vyrobiť", "a", "používať", "platobný", "prostriedok", "elektronický", "peniaz", "alebo", "iný", "platobný", "karty", "podľa", "§", "219", "ods", "1", "Tr", "zákon", "a", "iný", "Pokiaľ", "ido", "o", "trest", "súd", "upúšťať", "od", "uložiť", "súhrnný", "trest", "pretože", "pokladať", "súhrnný", "trest", "odňatia", "sloboda", "vo", "výmera", "5", "päť", "roky", "a", "10", "desať", "mesiac", "so", "zaradiť", "do", "ústav", "na", "výkon", "trest", "s", "minimálny", "stupeň", "stráženie", "ktorý", "byť", "obvinený", "uložiť", "rozsudok", "okresný", "súd", "Žilina", "sp", "zn", "1T/136/2011", "zo", "deň", "30", "11", "2011", "právoplatný", "a", "vykonateľný", "deň", "30", "11", "2011", "na", "ochranu", "spoločnosť", "a", "náprava", "páchateľ", "za", "dostatočný", "podľa", "§", "288", "ods", "1", "Tr", "por", "súd", "poškodený", "vzopäť", "p", "nar", "XX", "XX", "XXXX", "v", "A", "trvale", "byt", "ž", "Ul", "i", "č", "XXXX/XX", "odkazovať", "s", "jeho", "nárokom", "na", "náhrada", "škoda", "na", "občiansky", "súdny", "konať", "súd", "preskúmať", "návrh", "predložiť", "dohod", "o", "vina", "a", "trest", "s", "dôraz", "na", "splniť", "formálny", "i", "materiálny", "zákonný", "predpoklad", "na", "jej", "prijať", "súd", "zvlášť", "klásť", "dôraz", "na", "dôsledný", "rešpektovať", "právo", "obvinený", "na", "obhajoba", "a", "dodržiavať", "procesný", "predpis", "upravovať", "postup", "orgán", "činný", "v", "trestný", "konať", "súd", "následne", "môcť", "konštatovať", "že", "návrh", "dohod", "z", "formálny", "hľadisko", "jesť", "perfektný", "a", "súčasno", "nezistil", "také", "procesný", "pochybieť", "ktoré", "by", "mať", "za", "následok", "jej", "odmietnuť", "predložiť", "návrh", "dohod", "rešpektovať", "aj", "princíp", "pre", "ukladať", "trest", "a", "teda", "ju", "nemožno", "považovať", "za", "zrejme", "neprimeraný", "súd", "na", "verejný", "zasadnutie", "podľa", "§", "333", "ods", "3", "písm", "a", "až", "j", "Tr", "por", "zistil", "forma", "otázka", "či", "obvinený", "s", "i", "1", "rozumieť", "podať", "návrh", "na", "dohod", "o", "vina", "a", "trest", "2", "súhlasiť", "aby", "sa", "jeho", "trestný", "vec", "prejednať", "touto", "skrátiť", "forma", "čím", "sa", "vzdávať", "právo", "na", "verejný", "súdny", "proces", "3", "rozumieť", "čo", "tvoriť", "podstata", "skutok", "ktorý", "sa", "mu", "klásť", "za", "vina", "4", "či", "byť", "ako", "obvinený", "poučiť", "o", "svoji", "právo", "najmä", "o", "práve", "na", "obhajoba", "či", "mu", "byť", "dať", "možnosť", "na", "slobodný", "voľba", "obhajca", "a", "či", "sa", "s", "obhajca", "môcť", "radiť", "o", "spôsob", "obhajoba", "5", "rozumieť", "podstať", "konať", "o", "návrh", "na", "dohod", "o", "vina", "a", "trest", "6", "rozumieť", "právny", "kvalifikácia", "skutok", "ako", "trestný", "čin", "7", "byť", "oboznámiť", "s", "trestný", "sadzba", "ktoré", "zákon", "ustanovovať", "za", "trestný", "činy", "jemu", "klásť", "za", "vina", "8", "sa", "dobrovoľne", "priznať", "a", "uznať", "vina", "za", "spáchať", "skutok", "ktorý", "sa", "v", "návrh", "o", "dohod", "o", "vina", "a", "trest", "kvalifikovať", "ako", "určitý", "trestný", "čin", "9", "súhlasiť", "s", "navrhovať", "trest", "trest", "prijímať", "a", "v", "stanoviť", "lehota", "sa", "podriadiť", "výkon", "trest", "10", "si", "uvedomovať", "že", "ak", "súd", "príjme", "návrh", "na", "dohod", "o", "vina", "a", "trest", "a", "vyniesť", "rozsudok", "ktorý", "nadobudne", "právoplatnosť", "vyhlásiť", "nebude", "možný", "proti", "rozsudok", "podať", "odvolanie", "obvinený", "s", "i", "na", "všetok", "položiť", "otázka", "zrozumiteľne", "a", "určito", "slobodne", "a", "vážny", "odpovedať", "„áno“", "Touto", "forma", "si", "súd", "priamo", "u", "obvinený", "okrem", "iný", "overiť", "aj", "existencia", "závažný", "materiálny", "predpoklad", "dohod", "o", "vina", "a", "trest", "akým", "jesť", "priznať", "a", "uznanie", "vina", "obvinený", "podľa", "§", "334", "ods", "1", "Tr", "por", "súd", "môcť", "rozhodovať", "len", "o", "skutok", "jeho", "právny", "kvalifikácia", "primeranosť", "trest", "ochrannom", "opatriť", "vo", "vzťah", "k", "obvinený", "ako", "aj", "o", "výroku", "o", "náhrada", "škoda", "v", "rozsah", "uviesť", "v", "návrh", "na", "dohod", "o", "vina", "a", "trest", "ak", "obvinený", "na", "všetok", "otázka", "odpovedať", "„áno“", "vzhľadom", "k", "tomu", "že", "predložiť", "dohod", "o", "vina", "a", "trest", "v", "navrhnúť", "znenie", "nie", "jesť", "zrejme", "neprimeraný", "a", "jesť", "aj", "spravodlivý", "prič", "obvinený", "s", "i", "na", "všetok", "položiť", "otázka", "podľa", "§", "333", "ods", "3", "písm", "a/", "až", "j/", "Tr", "por", "odpovedať", "„áno“", "súd", "predložiť", "dohod", "o", "vina", "a", "trest", "schváliť", "a", "potvrdiť", "ju", "rozhodnúť", "ktoré", "jesť", "uviesť", "vo", "výroku", "tohto", "rozsudok", "rozsudok", "nadobudnúť", "právoplatnosť", "vyhlásiť", "poučiť", "p", "o", "u", "č", "e", "n", "i", "e", "proti", "tomuto", "rozsudok", "nie", "jesť", "prípustný", "odvolanie", "§", "334", "ods", "4", "Tr", "por", "dovolať", "ako", "mimoriadny", "opravný", "prostriedok", "jesť", "prípustný", "iba", "za", "podmienka", "uviesť", "v", "§", "371", "ods", "1", "písm", "vzopäť", "ods", "2", "Tr", "por"], "dokument_download_link": "", "datum_vydania_rozhodnutia": "", "odkazovane_predpisy_iri": "", "ecli": "", "vazby_na_eurlex": "", "vazby_na_eu_sudne_rozhodnutie": "", "vazby_na_sk_sudne_rozhodnutie": "", "index_timestamp": ""}