{"sud_guid": "", "sud_typ": "", "sud_nazov": "Okresný súd Levice", "guid": "", "sud_kraj": "", "sud_okres": "", "oblast_pravnej_upravy": [], "podoblast_pravnej_upravy": [], "forma_rozhodnutia": "", "povaha_rozhodnutia": ["Zmeňujúce"], "nadpis_rozhodnutia": "", "spisova_znacka": "11C/248/2015", "identifikacne_cislo_spisu": "", "sudca_guid": "", "sudca_meno": "", "sudca_meno_text": "", "odkazovane_predpisy": [], "dokument_nazov": "", "dokument_fulltext": ["súd", "okresný", "súd", "Levice", "spisový", "značka", "11C/248/2015", "identifikačný", "číslo", "súdny", "spis", "4315205323", "dátum", "vydať", "rozhodnúť", "26", "06", "2018", "meno", "a", "priezvisko", "sudca", "VSÚ", "JUDr", "Ľubica", "Cambelová", "ECLI", "ECLI", "SK", "OSLV", "2018", "4315205323", "4", "rozsudok", "v", "mena", "slovenský", "republika", "okresný", "súd", "Levice", "sudkyňa", "JUDr", "Ľubica", "Cambelovou", "Orange", "Slovensko", "a", "s", "IČO", "35697270", "Metodova", "8", "Bratislav", "zast", "bobák", "Bollová", "a", "spol", "s", "r", "o", "advokátsky", "kancelária", "so", "sídlo", "Dr", "Vladimíra", "Clementisa", "10", "Bratislav", "proti", "žalovaný", "d", "n", "t", "r", "XX", "XX", "XXXX", "d", "t", "XXXX/XX", "XXX", "XX", "q", "o", "r", "A", "Ľ", "x", "XXX", "XX", "q", "o", "zaplatiť", "175", "28", "eur", "s", "príslušenstvo", "rozhodnúť", "i", "žalovaný", "j", "e", "p", "o", "v", "i", "n", "n", "ý", "zaplatiť", "žalobca", "175", "28", "eur", "spolu", "s", "úrokom", "z", "omeškanie", "vo", "výška", "5", "25", "%", "ročne", "zo", "suma", "175", "28", "eur", "od", "29", "11", "2013", "do", "zaplatiť", "všetko", "do", "tri", "dniť", "od", "deň", "právoplatnosť", "rozsudok", "II", "žalobca", "vzdmúť", "á", "n", "á", "r", "o", "k", "na", "náhrada", "troviť", "konať", "proti", "žalovaný", "v", "rozsah", "100", "%", "odôvodnenie", "1", "žalobca", "v", "podať", "žaloba", "žiadal", "aby", "súd", "stanoviť", "žalovaný", "povinnosť", "zaplatiť", "žalobca", "175", "28", "eur", "spolu", "s", "úrokom", "z", "omeškanie", "vo", "výška", "5", "25", "%", "ročne", "z", "dlžný", "suma", "od", "29", "11", "2013", "do", "zaplatiť", "žalobca", "uviedol", "že", "so", "žalovaný", "uzavrieť", "zmluva", "č", "A1662845", "A7070586", "A4157125", "ktorých", "neoddeliteľný", "súčasť", "byť", "všeobecný", "podmienka", "v", "zmysle", "predmetný", "zmluva", "žalobca", "vypožičať", "žalovaný", "3", "ks", "SIM", "karta", "ktoré", "umožňovať", "žalovaný", "využívať", "telekomunikačný", "služba", "poskytovať", "žalobca", "SIM", "karty", "byť", "prideliť", "účastnícky", "telefónny", "číslo", "XXXXXXXXXX", "XXXXXXXXXX", "XXXXXXXXXX", "Tým", "že", "žalovaný", "riadne", "a", "včas", "zaplatiť", "cena", "za", "poskytnúť", "telekomunikačný", "služba", "za", "obdobie", "2013/7", "-", "2013/1", "porušiť", "zmluvný", "povinnosť", "žalobca", "zaslať", "žalovaný", "deň", "14", "11", "2013", "pokus", "o", "pokonávka", "s", "rozpis", "uhradiť", "faktúra", "za", "jednotlivý", "mesiac", "po", "zaslať", "pokus", "o", "pokonávka", "byť", "časť", "pohľadávka", "vo", "výška", "5", "eur", "odpísať", "a", "preto", "si", "ju", "žalobca", "v", "tomto", "konať", "uplatňovať", "žalovaný", "na", "pokus", "o", "pokonávka", "reagovať", "žiadnou", "ani", "čiastočný", "úhrada", "pohľadávka", "pohľadávka", "žalobca", "voči", "žalovaný", "z", "titul", "uhradiť", "služba", "predstavovať", "celkom", "suma", "175", "28", "eur", "žalobca", "si", "uplatňovať", "úrok", "z", "omeškanie", "z", "celkový", "dlžný", "suma", "v", "súlad", "so", "všeobecný", "podmienka", "čl", "11", "bod", "11", "14", "a", "to", "počať", "deň", "nasledovať", "po", "uplynúť", "lehota", "na", "dodatočný", "plniť", "uviesť", "v", "pokus", "o", "pokonávka", "t", "j", "od", "29", "11", "2013", "žalobca", "na", "preukázať", "svoji", "skutkový", "tvrdiť", "predložiť", "súd", "zmluva", "o", "pripojiť", "č", "A1662845", "zmluva", "o", "poskytovať", "verejný", "služba", "č", "A7070586", "zmluva", "o", "poskytovať", "verejný", "služba", "č", "A7070586", "pokus", "o", "pokonávka", "faktúra", "č", "5212394482", "č", "5216132920", "č", "5216066088", "č", "5215999074", "č", "5219772311", "č", "5219749374", "č", "52198145178", "č", "5219678852", "č", "5223344073", "č", "5223274138", "všeobecný", "podmienka", "2", "žalovaný", "v", "odpor", "podať", "proti", "platobný", "rozkaz", "okresný", "súd", "Levice", "zo", "deň", "7", "7", "2015", "pod", "č", "k", "11C/248/2015-31", "uviedol", "že", "uplatňovať", "nárok", "uznávať", "v", "celý", "rozsah", "pretože", "súd", "rozhodnúť", "iba", "na", "základ", "skutočnosť", "tvrdiť", "a", "preukázať", "žalobca", "poukázať", "na", "to", "že", "žalobca", "jesť", "dodávateľ", "a", "prieť", "uzatvárať", "predmetný", "zmluva", "ktoré", "označiť", "vo", "svoja", "žaloba", "postupovať", "v", "súlad", "so", "zákon", "a", "poskytnúť", "mu", "ako", "spotrebiteľ", "náležitý", "odborný", "starostlivosť", "považovať", "za", "nepravdivý", "tvrdiť", "žalobca", "že", "v", "zmysle", "predmetný", "zmluva", "žalobca", "vypožičať", "žalovaný", "3", "ks", "SIM", "karta", "zmluva", "obsahovať", "ustanovenie", "o", "vypožičať", "SIM", "karta", "nie", "jesť", "pravdivý", "podľa", "žalovaný", "tvrdiť", "žalobca", "že", "žalobca", "zaslať", "žalovaný", "deň", "14", "11", "2013", "pokus", "o", "pokonávka", "s", "rozpis", "uhradiť", "faktúra", "za", "jednotlivý", "mesiac", "nie", "jesť", "podľa", "žalovaný", "pravdivý", "tvrdiť", "žalobca", "že", "si", "žalovaný", "riadne", "a", "včas", "zaplatiť", "cena", "za", "poskytnúť", "telekomunikačný", "služba", "nie", "jesť", "tiež", "pravdivý", "tvrdiť", "žalobca", "že", "žalovaný", "porušiť", "zmluvný", "povinnosť", "uznávať", "uplatňovať", "úrok", "z", "omeškanie", "z", "celkový", "dlžný", "suma", "podľa", "žalobca", "v", "súlad", "so", "všeobecný", "podmienka", "čl", "11", "bod", "11", "14", "žalovaný", "poukázať", "na", "to", "že", "zmluva", "o", "pripojiť", "ktorú", "žalobca", "predložiť", "jesť", "zmluva", "spotrebiteľský", "formulárový", "predtlačiť", "typový", "a", "jej", "obsah", "spotrebiteľ", "mať", "možnosť", "ovplyvniť", "musieť", "ju", "podpísať", "tak", "ako", "mu", "byť", "predložiť", "zmluva", "obsahovať", "neprijateľný", "zmluvný", "podmienka", "napr", "zmluva", "zo", "4", "7", "2013", "bod", "7", "ustanovenie", "o", "riešiť", "spor", "v", "rozhodcovský", "konať", "pred", "stály", "rozhodcovský", "súd", "žalobca", "v", "zmluva", "dať", "podpísať", "spotrebiteľ", "ustanovenie", "že", "neoddeliteľný", "súčasť", "byť", "všeobecný", "podmienka", "poskytovať", "verejný", "elektronický", "komunikačný", "služba", "prostredníctvo", "verejný", "mobilný", "A", "sieť", "spoločnosť", "Orange", "Slovensko", "a", "s", "cenník", "služba", "a", "príloha", "k", "zmluva", "o", "poskytovať", "verejný", "služba", "s", "názvom", "„Súhlasy“", "čo", "spotrebiteľ", "podpísať", "avšak", "s", "uviesť", "príloha", "byť", "oboznámiť", "prečítať", "si", "ich", "z", "toho", "titul", "môcť", "byť", "nimi", "ani", "viazať", "nekalý", "praktika", "dodávateľ", "byť", "predtlačiť", "ustanovenie", "v", "zmluva", "a", "to", "súhlas", "s", "tým", "aby", "spoločnosť", "Orange", "Slovensko", "a", "s", "spracovávať", "spotrebiteľove", "prevádzkový", "a", "osobný", "údaj", "na", "marketingové", "účel", "najmä", "pre", "účel", "nový", "služba", "vrátane", "služba", "s", "pridať", "hodnota", "a", "ich", "uviesť", "na", "trh", "žalovaný", "nárok", "nie", "jesť", "jasný", "zrozumiteľný", "a", "určitý", "z", "dôvod", "že", "predmet", "zmluva", "byť", "služba", "Orange", "World", "mieň", "id", "kóda", "dynamický", "verejný", "IP", "adresa", "CLIR", "CLIP", "Roaming", "a", "blokovanie", "prichádzať", "hovor", "v", "roamingu", "a", "pretože", "v", "predložiť", "faktúra", "dohodnúť", "služba", "nie", "byť", "zohľadnené", "žalovaný", "uviedol", "že", "žalobca", "predložiť", "faktúra", "nezodpovedajú", "skutočnosť", "ani", "žalobný", "nároku", "žalovaný", "namietnuť", "pravosť", "predložiť", "faktúra", "ako", "dôkaz", "prič", "ani", "jeden", "z", "nich", "nie", "jesť", "v", "súlad", "so", "zákon", "podpísať", "oprávnený", "osoba", "tak", "ako", "jesť", "uviesť", "pre", "dodávateľ", "v", "obchodný", "register", "SR", "namietať", "predložiť", "faktúra", "z", "titul", "že", "spĺňať", "náležitosť", "doklad", "namietnuť", "aktívny", "vecný", "legitimácia", "žalobca", "z", "dôvod", "že", "žalobca", "predložiť", "súd", "plnomocenstvo", "účastník", "podpisovať", "ako", "v", "jeho", "menej", "zmluva", "žalovaný", "označiť", "a", "predložiť", "súd", "ako", "dôkaz", "žiadne", "listina", "3", "uznesenie", "zo", "deň", "3", "3", "2017", "č", "k", "11C/248/2015-44", "okresný", "súd", "Levice", "zrušil", "platobný", "rozkaz", "okresný", "súd", "Levice", "zo", "deň", "7", "7", "2015", "pod", "č", "k", "11C/248/2015-31", "4", "súd", "pojednávať", "v", "neprítomnosť", "strana", "spor", "pretože", "byť", "riadne", "predvolať", "a", "požiadať", "o", "odročiť", "pojednávanie", "z", "dôležitý", "dôvod", "žalovaný", "byť", "predvolať", "na", "pojednávanie", "z", "adresa", "ktorú", "uviedol", "ako", "korešpondenčný", "adresa", "Ľ", "x", "q", "o", "t", "z", "adresa", "ktorú", "mať", "viesť", "v", "register", "obyvateľ", "SR", "ako", "adresa", "trvalý", "pobyt", "t", "XXXX/XX", "q", "predvolanie", "na", "pojednávanie", "považovať", "sa", "z", "doručiť", "žalovaný", "s", "poukaz", "na", "§", "111", "ods", "3", "CSP", "v", "zmysle", "ktorého", "ak", "nemožno", "doručiť", "písomnosť", "na", "adresa", "podľa", "§", "106", "písomnosť", "sa", "považovať", "deň", "vrátiť", "doručiť", "zásielka", "súd", "za", "doručiť", "a", "to", "aj", "vtedy", "ak", "sa", "adresát", "o", "tom", "nedozvie", "súdny", "zásielka", "doručovať", "žalovaný", "na", "adresa", "Ľ", "x", "XXX", "XX", "q", "sa", "vrátiť", "súd", "ako", "doručiť", "23", "5", "2018", "a", "súdny", "zásielka", "doručovať", "na", "adresa", "t", "XXXX/XX", "XXX", "XX", "q", "sa", "vrátiť", "súd", "ako", "doručiť", "26", "4", "2018", "5", "súd", "na", "základ", "vykonať", "dokazovanie", "mať", "preukázať", "že", "žalobca", "uzavrieť", "so", "žalovaný", "tieto", "zmluva", "-", "zmluva", "o", "pripojiť", "č", "A1662845", "uzavrieť", "strana", "spor", "deň", "16", "12", "2004", "-", "zmluva", "o", "poskytovať", "verejný", "služba", "č", "A7070586", "uzavrieť", "strana", "spor", "deň", "4", "7", "2013", "-", "zmluva", "o", "pripojiť", "č", "A4157125", "uzavrieť", "strana", "spor", "deň", "19", "1", "2009", "neoddeliteľný", "súčasť", "všetkých", "týchto", "zmluva", "byť", "všeobecný", "podmienka", "na", "základ", "všetkých", "týchto", "zmluva", "byť", "žalovaný", "prideliť", "telefónny", "číslo", "byť", "prideliť", "SIM", "karta", "a", "byť", "dohodnúť", "účastnícky", "program", "a", "druh", "služba", "6", "podľa", "čl", "6", "bod", "6", "2", "písm", "b", "všeobecný", "podmienka", "okrem", "povinnosť", "upraviť", "v", "týchto", "všeobecný", "podmienka", "jesť", "účastník", "povinný", "platiť", "cena", "za", "poskytnúť", "služba", "podľa", "zmluva", "a", "podľa", "cenník", "ako", "aj", "cena", "za", "iný", "služba", "až", "na", "základ", "predložiť", "faktúra", "v", "súlad", "s", "ustanovenie", "článok", "11", "bod", "11", "8", "týchto", "všeobecný", "podmienka", "7", "žalobca", "vystaviť", "žalovaný", "nasledovný", "faktúra", "za", "poskytnúť", "mu", "služba", "č", "5212394482", "splatný", "22", "7", "2013na", "suma", "5", "03", "eur", "č", "5216132920", "splatný", "22", "8", "2013", "na", "suma", "7", "98", "eur", "č", "5216066088", "splatný", "22", "8", "2013", "na", "suma", "56", "22", "eur", "č", "5215999074", "splatný", "22", "8", "2013", "na", "suma", "64", "28", "eur", "č", "5219772311", "splatný", "22", "9", "2013", "na", "suma", "5", "eur", "č", "5219749374", "splatný", "22", "9", "2013", "na", "suma", "5", "94", "eur", "č", "52198145178", "splatný", "22", "9", "2013", "na", "suma", "8", "04", "eur", "č", "5219678852", "splatný", "22", "9", "2013", "na", "suma", "17", "05", "eur", "č", "5223344073", "splatný", "22", "10", "2013", "na", "suma", "0", "06", "eur", "č", "5223274138", "splatný", "22", "10", "2013", "na", "suma", "17", "74", "eur", "8", "z", "pokus", "o", "pokonávka", "z", "14", "11", "2013", "vyplývať", "že", "žalobca", "oznamovať", "žalovaný", "že", "evidovať", "voči", "nemu", "pohľadávka", "ktorá", "vzniknúť", "uhradiť", "faktúra", "za", "zúčtovací", "obdobie", "07/2013", "2", "99", "eur", "08/2013", "123", "46", "eur", "09/2013", "36", "03", "eur", "10/2013", "17", "80", "eur", "uvádzať", "ďalej", "že", "žalovaný", "jesť", "povinný", "zaplatiť", "aj", "poplatok", "za", "mimosúdne", "vymáhať", "14", "42", "eur", "podľa", "aktuálny", "platný", "všeobecný", "podmienka", "žalovaný", "byť", "vyzvať", "na", "úhrada", "suma", "194", "70", "eur", "najneskôr", "do", "28", "11", "2013", "9", "podľa", "§", "43", "ods", "1", "zák", "č", "610/2003", "z", "z", "v", "znenie", "platný", "a", "účinný", "ku", "deň", "uzavretie", "zmluva", "o", "pripojiť", "vzdmúť", "ďalej", "len", "zák", "č", "610/2003", "z", "z", "zmluva", "o", "pripojiť", "sa", "podnik", "zaväzovať", "účastník", "zriadiť", "potrebný", "prístup", "k", "verejný", "telefónny", "sieť", "alebo", "k", "iný", "verejný", "sieť", "a", "sprístupniť", "súvisiace", "služba", "súčasť", "zmluva", "byť", "všeobecný", "podmienka", "a", "tarifa", "10", "podľa", "§", "43", "ods", "2", "zák", "č", "610/2003", "z", "z", "podstatný", "časť", "zmluva", "o", "pripojiť", "byť", "dohodnúť", "druh", "verejný", "služba", "miesto", "jej", "poskytovať", "a", "cena", "za", "služba", "ak", "nie", "jesť", "v", "zmluva", "o", "pripojiť", "určiť", "čas", "poskytovať", "platiť", "že", "sa", "služba", "bude", "poskytovať", "na", "neurčitý", "čas", "cena", "za", "služba", "možno", "dojednať", "aj", "odkaz", "na", "tarifa", "11", "podľa", "§", "42", "ods", "4", "zák", "č", "610/2003", "z", "z", "účastník", "jesť", "povinný", "a", "používať", "verejný", "služba", "v", "súlad", "s", "týmto", "zákon", "so", "zmluva", "o", "pripojiť", "a", "so", "všeobecný", "podmienka", "b", "platiť", "cena", "za", "poskytnúť", "verejný", "služba", "podľa", "zmluva", "o", "pripojiť", "a", "podľa", "tarifa", "a", "ak", "to", "povaha", "služba", "umožňovať", "až", "na", "základ", "predložiť", "doklad", "o", "vyúčtovanie", "vzopäť", "používať", "iba", "telekomunikačný", "zariadenie", "spĺňať", "požiadavka", "osobitný", "predpis", "12", "podľa", "§", "44", "ods", "1", "zák", "č", "351/2011", "z", "z", "zmluva", "o", "poskytovať", "verejný", "služba", "sa", "podnik", "zaväzovať", "účastník", "zriadiť", "potrebný", "pripojiť", "k", "verejný", "sieť", "alebo", "poskytovať", "príslušný", "služba", "podnik", "môcť", "vydať", "všeobecný", "podmienka", "a", "cenník", "ktoré", "byť", "súčasť", "zmluva", "zmluva", "o", "poskytovať", "verejný", "služba", "jesť", "písomná;", "to", "platiť", "pre", "predplatiť", "služba", "poskytovať", "služba", "prostredníctvo", "verejný", "telefónny", "automat", "a", "iný", "verejný", "prístupových", "bod", "písomný", "zmluva", "o", "poskytovať", "verejný", "služba", "jesť", "možný", "meniť", "aj", "iný", "ako", "písomný", "forma", "ak", "sa", "na", "tom", "zmluvný", "strana", "dohodnú;", "to", "platiť", "pre", "záväzok", "účastník", "ktoré", "podľa", "občiansky", "zákonník", "možno", "dojednať", "len", "v", "písomný", "forma", "13", "podľa", "§", "43", "ods", "12", "písm", "b", "zák", "č", "351/2011", "z", "z", "účastník", "jesť", "povinný", "platiť", "za", "poskytnúť", "verejný", "služba", "podľa", "zmluva", "o", "poskytovať", "verejný", "služba", "a", "ak", "to", "povaha", "služba", "umožňovať", "až", "na", "základ", "predložiť", "faktúra", "14", "podľa", "§", "52", "ods", "3", "o", "z", "ustanovenie", "o", "spotrebiteľský", "zmluva", "ako", "aj", "všetok", "iný", "ustanovenie", "upravovať", "právny", "vzťah", "ktorých", "účastník", "jesť", "spotrebiteľ", "použijú", "sa", "vždy", "ak", "jesť", "to", "na", "prospech", "zmluvný", "strana", "ktorá", "jesť", "spotrebiteľ", "odlišný", "zmluvný", "dojednať", "alebo", "dohod", "ktorých", "obsah", "alebo", "účel", "jesť", "obchádzať", "tohto", "ustanovenie", "byť", "neplatný", "na", "všetok", "právny", "vzťah", "ktorých", "účastník", "jesť", "spotrebiteľ", "sa", "vždy", "prednostne", "použijú", "ustanovenie", "občiansky", "zákonník", "aj", "keď", "by", "sa", "inak", "mať", "použiť", "norma", "obchodný", "právo", "15", "podľa", "§", "52", "ods", "3", "o", "z", "dodávateľ", "jesť", "osoba", "ktorá", "prieť", "uzatvárať", "a", "plnený", "spotrebiteľský", "zmluva", "konať", "v", "rámec", "predmet", "svoja", "obchodný", "alebo", "iný", "podnikateľský", "činnosť", "16", "podľa", "§", "52", "ods", "4", "o", "z", "spotrebiteľ", "jesť", "fyzický", "osoba", "ktorá", "prieť", "uzatvárať", "a", "plnený", "spotrebiteľský", "zmluva", "konať", "v", "rámec", "predmet", "svoja", "obchodný", "činnosť", "alebo", "iný", "podnikateľský", "činnosť", "17", "podľa", "§", "54", "ods", "1", "o", "z", "zmluvný", "podmienka", "upraviť", "spotrebiteľský", "zmluva", "sa", "môcť", "odchýliť", "od", "tohto", "zákon", "v", "neprospech", "spotrebiteľ", "spotrebiteľ", "sa", "najmä", "môcť", "vopred", "vzdať", "svoji", "právo", "ktoré", "mu", "tento", "zákon", "alebo", "osobitný", "predpis", "na", "ochranu", "spotrebiteľ", "priznávať", "alebo", "si", "inak", "zhoršiť", "svoje", "zmluvný", "postavenie", "18", "súd", "na", "základ", "vykonať", "dokazovanie", "dospieť", "k", "záver", "že", "jesť", "dôvodný", "žaloba", "vyhovieť", "súd", "mať", "preukázať", "že", "medza", "strana", "spor", "došlo", "k", "uzavretie", "zmluva", "o", "pripojiť", "16", "12", "2004", "č", "A", "7070586", "zmluva", "o", "poskytovať", "verejný", "služba", "4", "7", "2013", "č", "A7070586", "zmluva", "o", "pripojiť", "z", "19", "1", "2009", "č", "A", "4157125", "v", "zmluva", "jesť", "uviesť", "že", "byť", "prideliť", "žalovaný", "SIM", "karta", "jesť", "uviesť", "číslo", "SIM", "karty", "jesť", "uviesť", "aj", "telefónny", "číslo", "dohodnúť", "účastnícky", "program", "a", "dohodnúť", "služba", "zo", "zmluva", "vyplývať", "že", "v", "každej", "zmluva", "za", "predávať", "-", "žalobca", "jesť", "uviesť", "kóda", "predajný", "miesto", "meno", "a", "priezvisko", "predajcu", "a", "názov", "predajný", "miesto", "na", "základ", "uviesť", "zmluva", "žalobca", "poskytovať", "žalovaný", "služba", "a", "žalovaný", "vzniknúť", "povinnosť", "na", "základ", "týchto", "zmluva", "platiť", "cena", "poskytnúť", "služba", "19", "z", "predložiť", "vyššieoznačených", "faktúra", "vyplývať", "že", "žalovaný", "byť", "vyfakturovať", "cena", "poskytovať", "mu", "služba", "žalovaný", "uvádzať", "že", "nie", "jesť", "pravdivý", "tvrdiť", "že", "si", "žalovaný", "riadne", "a", "včas", "zaplatiť", "cena", "za", "poskytovať", "telekomunikačný", "služba", "avšak", "predložiť", "žiadne", "dôkaz", "na", "základ", "ktorých", "by", "preukázať", "že", "fakturovať", "cena", "služba", "na", "základ", "faktúra", "žalobca", "uhradiť", "dátum", "splatnosť", "faktúra", "vyplynúť", "z", "údaj", "o", "splatnosť", "na", "jednotlivý", "faktúra", "nie", "jesť", "preto", "rozhodovať", "či", "žalovaný", "prevziať", "pokus", "o", "pokonávka", "zo", "14", "11", "2013", "žalovaný", "byť", "povinný", "užiť", "na", "základ", "faktúra", "fakturovať", "mu", "cena", "služba", "žalobca", "do", "termín", "splatnosť", "faktúra", "uhradiť", "žalobca", "vzniknúť", "povinnosť", "v", "zmysle", "uzavretý", "zmluva", "ktorých", "súčasť", "byť", "aj", "všeobecný", "podmienka", "cena", "služba", "žalobca", "platiť", "na", "základ", "faktúra", "žalovaný", "preukázať", "že", "si", "túto", "svoja", "povinnosť", "splniť", "pokiaľ", "ido", "o", "vyššieoznačené", "faktúra", "v", "suma", "uplatniť", "v", "žaloba", "samotný", "skutočnosť", "že", "v", "zmluva", "byť", "uvádzať", "zmluvný", "podmienka", "o", "riešiť", "spor", "v", "rozhodcovský", "konať", "a", "že", "v", "zmluva", "byť", "predtlačiť", "súhlas", "s", "tým", "aby", "spoločnosť", "Orange", "Slovensko", "a", "s", "spracovávať", "spotrebiteľove", "prevádzkový", "a", "osobný", "údaj", "najmä", "na", "marketingové", "účel", "mať", "vplyv", "na", "záväzok", "žalovaný", "platiť", "riadne", "a", "včas", "cena", "služba", "20", "Pokiaľ", "ido", "o", "to", "že", "faktúra", "byť", "podpísať", "oprávnený", "osoba", "ako", "jesť", "uviesť", "v", "obchodný", "register", "SR", "súd", "poukazovať", "na", "to", "že", "faktúra", "nie", "byť", "povinný", "podpisovať", "osoba", "oprávnený", "konať", "za", "spoločnosť", "Orange", "Slovensko", "a", "s", "uviesť", "v", "obchodný", "register", "SR", "keďže", "v", "dať", "prípad", "byť", "faktúra", "bežne", "vystaviť", "tými", "ktorí", "byť", "poverenie", "v", "obchodný", "spoločnosť", "touto", "činnosť", "žalovaný", "nespochybnil", "nárok", "žalobca", "na", "zaplatiť", "suma", "175", "28", "eur", "a", "preukázať", "že", "uviesť", "dlžný", "suma", "na", "základ", "faktúra", "žalobca", "zaplatiť", "súd", "preto", "stanoviť", "žalovaný", "povinnosť", "zaplatiť", "žalobca", "175", "28", "eur", "žalovaný", "sa", "dostať", "do", "omeškanie", "so", "zaplatiť", "jednotlivo", "fakturovať", "mu", "suma", "na", "základ", "vyššieuvedených", "faktúra", "vždy", "od", "nasledovať", "deň", "po", "splatnosť", "tej-", "ktorej", "faktúra", "vzniknúť", "mu", "preto", "povinnosť", "zaplatiť", "žalobca", "aj", "úrok", "z", "omeškanie", "užiť", "od", "deň", "nasledovať", "po", "splatnosť", "faktúra", "žalobca", "si", "nárok", "na", "zaplatiť", "suma", "celkove", "175", "28", "eur", "uplatňovať", "od", "neskoršieho", "termín", "a", "to", "od", "nasledovať", "deň", "po", "uplynúť", "lehota", "na", "zaplatiť", "ktorá", "byť", "stanoviť", "v", "pokus", "o", "pokonávka", "do", "28", "11", "2013", "súd", "preto", "stanoviť", "povinnosť", "žalovaný", "zaplatiť", "žalobca", "úrok", "z", "omeškanie", "od", "29", "11", "2013", "vo", "výška", "5", "25", "%", "ročne", "zo", "suma", "175", "28", "eur", "do", "zaplatiť", "21", "podľa", "§", "255", "ods", "1", "CSP", "súd", "priznať", "strana", "náhrada", "troviť", "konať", "podľa", "pomer", "jej", "úspech", "vo", "vec", "22", "žalobca", "mať", "v", "konať", "úplný", "procesný", "úspech", "súd", "preto", "rozhodnúť", "že", "žalobca", "mať", "nárok", "na", "náhrada", "troviť", "konať", "proti", "žalovaný", "v", "rozsah", "100", "%", "poučiť", "proti", "tomuto", "rozsudok", "možno", "podať", "odvolanie", "v", "lehota", "15", "dniť", "od", "deň", "doručiť", "rozsudok", "na", "okresný", "súd", "Levice", "v", "dva", "písomný", "vyhotovenie", "podľa", "§", "363", "CSP", "v", "odvolanie", "sa", "popri", "všeobecný", "náležitosť", "podať", "uviesť", "proti", "ktorému", "rozhodnúť", "smerovať", "v", "ak", "rozsah", "sa", "napádať", "z", "akých", "dôvod", "sa", "rozhodnúť", "považovať", "za", "nesprávny", "odvolací", "dôvod", "a", "čoho", "sa", "odvolateľ", "domáhať", "odvolací", "návrh", "podľa", "§", "364", "CSP", "rozsah", "v", "ak", "sa", "rozhodnúť", "napádať", "môcť", "odvolateľ", "rozšíriť", "len", "do", "uplynúť", "lehota", "na", "podať", "odvolanie", "podľa", "§", "365", "ods", "1", "CSP", "odvolanie", "možno", "odôvodniť", "len", "tým", "že", "a", "byť", "splniť", "procesný", "podmienka", "b", "súd", "nesprávny", "procesný", "postup", "znemožnil", "strana", "aby", "uskutočňovať", "jej", "patriť", "procesný", "právo", "v", "takej", "mier", "že", "došlo", "k", "porušiť", "právo", "na", "spravodlivý", "proces", "vzopäť", "rozhodovať", "vylúčiť", "sudca", "alebo", "nesprávny", "obsadiť", "súd", "d", "konať", "mať", "iný", "vada", "ktorá", "mohla", "mať", "za", "následok", "nesprávny", "rozhodnúť", "vo", "vec", "e", "súd", "prvej", "inštancia", "vykonať", "navrhnúť", "dôkaz", "potrebný", "na", "zistenie", "rozhodovať", "skutočnosť", "f", "súd", "prvej", "inštancia", "dospieť", "na", "základ", "vykonať", "dôkaz", "k", "nesprávny", "skutkový", "zisteniam", "g", "zistený", "skutkový", "staviť", "obstáť", "pretože", "byť", "prípustný", "ďalší", "prostriedok", "procesný", "obrana", "alebo", "ďalší", "prostriedok", "procesný", "útoku", "ktoré", "byť", "uplatniť", "alebo", "h", "rozhodnúť", "súd", "prvej", "inštancia", "vychádzať", "z", "nesprávny", "právny", "posúdenie", "vec", "podľa", "§", "365", "ods", "2", "CSP", "odvolanie", "proti", "rozhodnúť", "vo", "vec", "samej", "možno", "odôvodniť", "aj", "tým", "že", "právoplatný", "uznesenie", "súd", "prvej", "inštancia", "ktoré", "predchádzať", "rozhodnúť", "vo", "vec", "samej", "mať", "vada", "uviesť", "v", "odsek", "1", "ak", "táto", "vada", "mať", "vplyv", "na", "rozhodnúť", "vo", "vec", "samej", "podľa", "§", "365", "ods", "3", "CSP", "odvolací", "dôvod", "a", "dôkaz", "na", "ich", "preukázať", "možno", "meniť", "a", "dopĺňať", "len", "do", "uplynúť", "lehota", "na", "podať", "odvolanie", "ak", "povinný", "dobrovoľne", "splniť", "čo", "mu", "ukladať", "vykonateľný", "rozhodnúť", "oprávnený", "môcť", "podať", "návrh", "na", "vykonať", "exekúcia", "podľa", "osobitný", "predpis"], "dokument_download_link": "", "datum_vydania_rozhodnutia": "", "odkazovane_predpisy_iri": "", "ecli": "", "vazby_na_eurlex": "", "vazby_na_eu_sudne_rozhodnutie": "", "vazby_na_sk_sudne_rozhodnutie": "", "index_timestamp": ""}